iiif/__init__.py
iiif/_version.py
iiif/example.py
iiif/iiif.py
iiif/static/016da063e45add4f7f353eb87f2de5d7.png
iiif/static/028df665ba465133ea20a5f7d8f7a45b.png
iiif/static/0478bc0721361e245bc6ae7b80d07bb2.png
iiif/static/1750b0b6fb8f23fb343a3bd595741cbd.png
iiif/static/19662f7ca1c1a896c95bd760c0f6a31e.png
iiif/static/1ac9f6bd7fd35cfe81abe8ec516a7ad0.png
iiif/static/1d86f5b8002be1d5542cdd5dfb00e0b3.png
iiif/static/219ca15281bf30ca42fc9b041baa0f81.png
iiif/static/34fcccb901abeecf9731594b4ca70887.png
iiif/static/42e9c79dc79375d102153858e669bd30.png
iiif/static/4f2a6dd2d0d4ffdf350ef253d17e45b0.png
iiif/static/504f56a785ab7f6da4a0415f1c16f6b4.png
iiif/static/520d9665fb306f55bbf589cd94a12dee.png
iiif/static/52688ff690266b2055752e3aa91f9009.png
iiif/static/5b21ffaa3340353be073ecedad1d5d0a.png
iiif/static/5f8e933291cf779d715ded0ab4759692.png
iiif/static/65336ac83e6674247de68e1363a916a0.png
iiif/static/6a4823da6ccb5a7d4d7a2dde4b19d5e6.png
iiif/static/6c78c2bc7bea7254506283208b553bb8.png
iiif/static/6d65f1f8fcc0ef137c1a0b9226dc7147.png
iiif/static/71845fb2fc9a756e824778d101b06157.png
iiif/static/7a66a59675febabbe9b4d30f0b1a0aeb.png
iiif/static/7b852cf8cc419742f33c0796a375c790.png
iiif/static/803fa7192e5aa0bdb9dea5f78db5705a.png
iiif/static/830a1f39be3cadaabedda812424ec763.png
iiif/static/8d9fa38f7e0cd6d66f7c6927095e67a4.png
iiif/static/92c4eed280c1bed37c9fba0aae7cca88.png
iiif/static/9939873c8af89939e7c5be4db4dab447.png
iiif/static/af78a3af12bcf393b01f74f9b3e37a6a.png
iiif/static/b08af14c739a8482ddc495184adb21c3.png
iiif/static/b2eb667c796530057e17ec05556c8a30.png
iiif/static/c6327813723b52b9eabc1952626c99df.png
iiif/static/d14125142ef3694d56fd8a29fa32e2c6.png
iiif/static/d7168de399c639756fad56a7b877938a.png
iiif/static/extension.js
iiif/static/f34fb64dfbb2bfdd2e0d54478ec8e7cc.png
iiif/static/f3a4dc16ec7028978d3c334073a9c36c.png
iiif/static/iiif.css
iiif/static/index.js
iiif/static/index.js.map
ipyiiif-0.3.0a0.dist-info/DESCRIPTION.rst
ipyiiif-0.3.0a0.dist-info/METADATA
ipyiiif-0.3.0a0.dist-info/RECORD
ipyiiif-0.3.0a0.dist-info/WHEEL
ipyiiif-0.3.0a0.dist-info/metadata.json
ipyiiif-0.3.0a0.dist-info/top_level.txt
